novara/commands/configure.py
novara/commands/generate.py
novara/commands/info.py
novara/commands/init.py
novara/commands/logs.py
novara/commands/pull.py
novara/commands/remove.py
novara/commands/run.py
novara/commands/status.py
novara/commands/stop.py
novara/commands/version.py
novara/config.py
novara/constants.py
novara/guess.py
novara/main.py
novara/request.py
novara/utils.py
novara-0.1.22.dist-info/METADATA
novara-0.1.22.dist-info/WHEEL
novara-0.1.22.dist-info/entry_points.txt
novara-0.1.22.dist-info/RECORD
