Metadata-Version: 2.4
Name: novara
Version: 0.1.22
Summary: 
Requires-Python: >=3.10,<4.0
Classifier: Programming Language :: Python :: 3
Classifier: Programming Language :: Python :: 3.10
Classifier: Programming Language :: Python :: 3.11
Classifier: Programming Language :: Python :: 3.12
Classifier: Programming Language :: Python :: 3.13
Classifier: Programming Language :: Python :: 3.14
Requires-Dist: PyYAML (>=6.0.2,<7.0.0)
Requires-Dist: auto-click-auto (>=0.1.5,<0.2.0)
Requires-Dist: click (>=8.1.7,<9.0.0)
Requires-Dist: docker (>=7.1.0,<8.0.0)
Requires-Dist: pydantic (>=2.9.2,<3.0.0)
Requires-Dist: python-box (>=7.2.0,<8.0.0)
Requires-Dist: questionary (>=2.0.1,<3.0.0)
Requires-Dist: requests (>=2.32.3,<3.0.0)
Requires-Dist: rich (>=13.8.0,<14.0.0)
Requires-Dist: rich-click (>=1.8.3,<2.0.0)
Requires-Dist: toml (>=0.10.2,<0.11.0)
